misspy_packager/__init__.py
misspy_packager/main.py
misspy_packager/packager.py
misspy_packager-0.2.4.dist-info/entry_points.txt
misspy_packager-0.2.4.dist-info/METADATA
misspy_packager-0.2.4.dist-info/WHEEL
misspy_packager-0.2.4.dist-info/RECORD
